odoo/addons/event_session/README.rst
odoo/addons/event_session/__init__.py
odoo/addons/event_session/__manifest__.py
odoo/addons/event_session/controllers/__init__.py
odoo/addons/event_session/controllers/main.py
odoo/addons/event_session/data/event_session_timeslot.xml
odoo/addons/event_session/data/mail_template.xml
odoo/addons/event_session/demo/event_session.xml
odoo/addons/event_session/i18n/es.po
odoo/addons/event_session/i18n/event_session.pot
odoo/addons/event_session/i18n/fr.po
odoo/addons/event_session/i18n/it.po
odoo/addons/event_session/i18n/nl.po
odoo/addons/event_session/migrations/18.0.1.0.0/noupdate_changes.xml
odoo/addons/event_session/migrations/18.0.1.0.0/post-migration.py
odoo/addons/event_session/models/__init__.py
odoo/addons/event_session/models/event_event.py
odoo/addons/event_session/models/event_mail.py
odoo/addons/event_session/models/event_mail_registration.py
odoo/addons/event_session/models/event_mail_session.py
odoo/addons/event_session/models/event_registration.py
odoo/addons/event_session/models/event_session.py
odoo/addons/event_session/models/event_session_timeslot.py
odoo/addons/event_session/models/event_type.py
odoo/addons/event_session/readme/CONTRIBUTORS.md
odoo/addons/event_session/readme/DESCRIPTION.md
odoo/addons/event_session/readme/ROADMAP.md
odoo/addons/event_session/readme/USAGE.md
odoo/addons/event_session/reports/event_report_templates.xml
odoo/addons/event_session/security/ir.model.access.csv
odoo/addons/event_session/security/security.xml
odoo/addons/event_session/static/description/icon.png
odoo/addons/event_session/static/description/index.html
odoo/addons/event_session/tests/__init__.py
odoo/addons/event_session/tests/common.py
odoo/addons/event_session/tests/test_event_session.py
odoo/addons/event_session/tests/test_event_session_ics.py
odoo/addons/event_session/tests/test_event_session_mail.py
odoo/addons/event_session/tests/test_event_session_wizard.py
odoo/addons/event_session/views/event_event.xml
odoo_addon_event_session-18.0.1.0.0.11.dist-info/METADATA
odoo_addon_event_session-18.0.1.0.0.11.dist-info/WHEEL
odoo_addon_event_session-18.0.1.0.0.11.dist-info/top_level.txt
odoo_addon_event_session-18.0.1.0.0.11.dist-info/RECORD
