Metadata-Version: 2.1
Name: odoo-addon-event_session
Version: 18.0.1.0.0.11
Requires-Python: >=3.10
Requires-Dist: odoo==18.0.*
Summary: Sessions in events
Home-page: https://github.com/OCA/event
License: AGPL-3
Author: Tecnativa, Odoo Community Association (OCA)
Author-email: support@odoo-community.org
Classifier: Programming Language :: Python
Classifier: Framework :: Odoo
Classifier: Framework :: Odoo :: 18.0
Classifier: License :: OSI Approved :: GNU Affero General Public License v3
